{
  "Role": {
    "elements": [
      {
        "shape": "round_rectangle",
        "width": 160,
        "height": 60,
        "rotation": 0,
        "style": {
          "fillColor": "tokens.color.yellow[150]",
          "fontFamily": "Arial"
        },
        "text": "{{label}}"
      }
    ]
  },
  "BusinessService": {
    "elements": [
      {
        "shape": "round_rectangle",
        "width": 160,
        "height": 60,
        "style": {
          "fillColor": "tokens.color.blue[200]",
          "fontFamily": "Arial"
        },
        "text": "{{label}}"
      }
    ]
  },
  "BusinessProcess": {
    "elements": [
      {
        "shape": "round_rectangle",
        "width": 160,
        "height": 60,
        "style": {
          "fillColor": "tokens.color.green[150]",
          "fontFamily": "Arial"
        },
        "text": "{{label}}"
      }
    ]
  },
  "ApplicationComponent": {
    "elements": [
      {
        "shape": "round_rectangle",
        "width": 160,
        "height": 60,
        "style": {
          "fillColor": "tokens.color.blue[100]",
          "fontFamily": "Arial"
        },
        "text": "{{label}}"
      }
    ]
  },
  "DataObject": {
    "elements": [
      {
        "shape": "rectangle",
        "width": 160,
        "height": 60,
        "style": {
          "fillColor": "tokens.color.yellow[250]",
          "fontFamily": "Arial"
        },
        "text": "{{label}}"
      }
    ]
  },
  "Device": {
    "elements": [
      {
        "shape": "rectangle",
        "width": 160,
        "height": 60,
        "style": {
          "fillColor": "tokens.color.gray[200]",
          "fontFamily": "Arial"
        },
        "text": "{{label}}"
      }
    ]
  },
  "BusinessActor": {
    "elements": [
      {
        "shape": "round_rectangle",
        "width": 160,
        "height": 60,
        "style": {
          "fillColor": "tokens.color.yellow[200]",
          "fontFamily": "Arial"
        },
        "text": "{{label}}"
      }
    ]
  },
  "ApplicationService": {
    "elements": [
      {
        "shape": "round_rectangle",
        "width": 160,
        "height": 60,
        "style": {
          "fillColor": "tokens.color.blue[200]",
          "fontFamily": "Arial"
        },
        "text": "{{label}}"
      }
    ]
  },
  "Node": {
    "elements": [
      {
        "shape": "rectangle",
        "width": 160,
        "height": 60,
        "style": {
          "fillColor": "tokens.color.gray[200]",
          "fontFamily": "Arial"
        },
        "text": "{{label}}"
      }
    ]
  },
  "TechnologyService": {
    "elements": [
      {
        "shape": "round_rectangle",
        "width": 160,
        "height": 60,
        "style": {
          "fillColor": "tokens.color.blue[150]",
          "fontFamily": "Arial"
        },
        "text": "{{label}}"
      }
    ]
  },
  "WorkPackage": {
    "elements": [
      {
        "shape": "round_rectangle",
        "width": 160,
        "height": 60,
        "style": {
          "fillColor": "tokens.color.red[150]",
          "fontFamily": "Arial"
        },
        "text": "{{label}}"
      }
    ]
  },
  "Goal": {
    "elements": [
      {
        "shape": "round_rectangle",
        "width": 160,
        "height": 60,
        "style": {
          "fillColor": "tokens.color.red[200]",
          "fontFamily": "Arial"
        },
        "text": "{{label}}"
      }
    ]
  },
  "Decision": {
    "elements": [
      {
        "shape": "diamond",
        "width": 80,
        "height": 80,
        "style": {
          "fillColor": "tokens.color.yellow[200]",
          "fontFamily": "Arial"
        },
        "text": "{{label}}"
      }
    ]
  },
  "StartEnd": {
    "elements": [
      {
        "shape": "ellipse",
        "width": 100,
        "height": 60,
        "style": {
          "fillColor": "tokens.color.yellow[250]",
          "fontFamily": "Arial"
        },
        "text": "{{label}}"
      }
    ]
  }
}
